{
  "image_id": "chip_0385",
  "width": 256,
  "height": 256,
  "total_pins": 14,
  "pins": [
    {
      "pin_number": 1,
      "name": "D7",
      "bbox_pin": [
        78,
        32,
        86,
        44
      ],
      "bbox_name": [
        33,
        32,
        51,
        44
      ]
    },
    {
      "pin_number": 2,
      "name": "SDI",
      "bbox_pin": [
        78,
        62,
        86,
        74
      ],
      "bbox_name": [
        33,
        62,
        56,
        74
      ]
    },
    {
      "pin_number": 3,
      "name": "AD0",
      "bbox_pin": [
        78,
        92,
        86,
        104
      ],
      "bbox_name": [
        33,
        92,
        61,
        104
      ]
    },
    {
      "pin_number": 4,
      "name": "PROG",
      "bbox_pin": [
        78,
        122,
        86,
        134
      ],
      "bbox_name": [
        33,
        122,
        74,
        134
      ]
    },
    {
      "pin_number": 5,
      "name": "TXD",
      "bbox_pin": [
        78,
        152,
        86,
        164
      ],
      "bbox_name": [
        33,
        152,
        61,
        164
      ]
    },
    {
      "pin_number": 6,
      "name": "MOSI",
      "bbox_pin": [
        78,
        182,
        86,
        194
      ],
      "bbox_name": [
        33,
        182,
        69,
        194
      ]
    },
    {
      "pin_number": 7,
      "name": "VOUT",
      "bbox_pin": [
        78,
        212,
        86,
        224
      ],
      "bbox_name": [
        33,
        212,
        72,
        224
      ]
    },
    {
      "pin_number": 14,
      "name": "A0",
      "bbox_pin": [
        173,
        32,
        189,
        44
      ],
      "bbox_name": [
        203,
        32,
        221,
        44
      ]
    },
    {
      "pin_number": 13,
      "name": "TDO",
      "bbox_pin": [
        173,
        62,
        189,
        74
      ],
      "bbox_name": [
        203,
        62,
        233,
        74
      ]
    },
    {
      "pin_number": 12,
      "name": "RF",
      "bbox_pin": [
        173,
        92,
        189,
        104
      ],
      "bbox_name": [
        203,
        92,
        222,
        104
      ]
    },
    {
      "pin_number": 11,
      "name": "TEMP",
      "bbox_pin": [
        173,
        122,
        189,
        134
      ],
      "bbox_name": [
        203,
        122,
        242,
        134
      ]
    },
    {
      "pin_number": 10,
      "name": "HOLD",
      "bbox_pin": [
        173,
        152,
        189,
        164
      ],
      "bbox_name": [
        203,
        152,
        242,
        164
      ]
    },
    {
      "pin_number": 9,
      "name": "RXD",
      "bbox_pin": [
        173,
        182,
        181,
        194
      ],
      "bbox_name": [
        203,
        182,
        232,
        194
      ]
    },
    {
      "pin_number": 8,
      "name": "A2",
      "bbox_pin": [
        173,
        212,
        181,
        224
      ],
      "bbox_name": [
        203,
        212,
        221,
        224
      ]
    }
  ]
}