{
  "image_id": "CSCG04828_7_1",
  "width": 1161,
  "height": 1020,
  "total_pins": 66,
  "package_type": "4side",
  "pins": [
    {
      "pin_number": "00",
      "name": "MISS",
      "bbox_pin": null,
      "bbox_name": null
    },
    {
      "pin_number": "1",
      "name": "DCLKOUT0",
      "bbox_pin": null,
      "bbox_name": null
    },
    {
      "pin_number": "2",
      "name": "DCLKOUT0*",
      "bbox_pin": null,
      "bbox_name": null
    },
    {
      "pin_number": "3",
      "name": "SDCLKOU1",
      "bbox_pin": null,
      "bbox_name": null
    },
    {
      "pin_number": "4",
      "name": "SDCLKOU1*",
      "bbox_pin": null,
      "bbox_name": null
    },
    {
      "pin_number": "5",
      "name": "RESET/GPO",
      "bbox_pin": null,
      "bbox_name": null
    },
    {
      "pin_number": "06",
      "name": "DCLKOU2",
      "bbox_pin": null,
      "bbox_name": null
    },
    {
      "pin_number": "6",
      "name": "SYNC/SYSREFREQ",
      "bbox_pin": null,
      "bbox_name": null
    },
    {
      "pin_number": "7",
      "name": "NC",
      "bbox_pin": null,
      "bbox_name": null
    },
    {
      "pin_number": "8",
      "name": "NC",
      "bbox_pin": null,
      "bbox_name": null
    },
    {
      "pin_number": "9",
      "name": "NC",
      "bbox_pin": null,
      "bbox_name": null
    },
    {
      "pin_number": "10",
      "name": "MISS",
      "bbox_pin": null,
      "bbox_name": null
    },
    {
      "pin_number": "11",
      "name": "LDOBYP1",
      "bbox_pin": null,
      "bbox_name": null
    },
    {
      "pin_number": "12",
      "name": "LDOBVP2",
      "bbox_pin": null,
      "bbox_name": null
    },
    {
      "pin_number": "13",
      "name": "MISS",
      "bbox_pin": null,
      "bbox_name": null
    },
    {
      "pin_number": "14",
      "name": "MISS",
      "bbox_pin": null,
      "bbox_name": null
    },
    {
      "pin_number": "15",
      "name": "DCLKOUT2",
      "bbox_pin": null,
      "bbox_name": null
    },
    {
      "pin_number": "16",
      "name": "MISS",
      "bbox_pin": null,
      "bbox_name": null
    },
    {
      "pin_number": "17",
      "name": "VCCC2_CG1",
      "bbox_pin": null,
      "bbox_name": null
    },
    {
      "pin_number": "18",
      "name": "MISS",
      "bbox_pin": null,
      "bbox_name": null
    },
    {
      "pin_number": "19",
      "name": "MISS",
      "bbox_pin": null,
      "bbox_name": null
    },
    {
      "pin_number": "20",
      "name": "SDIO",
      "bbox_pin": null,
      "bbox_name": null
    },
    {
      "pin_number": "21",
      "name": "CCC3_SYSREF",
      "bbox_pin": null,
      "bbox_name": null
    },
    {
      "pin_number": "22",
      "name": "SDCLKOU5",
      "bbox_pin": null,
      "bbox_name": null
    },
    {
      "pin_number": "23",
      "name": "SDCLKOU5",
      "bbox_pin": null,
      "bbox_name": null
    },
    {
      "pin_number": "24",
      "name": "MISS",
      "bbox_pin": null,
      "bbox_name": null
    },
    {
      "pin_number": "25",
      "name": "DCLKOU4",
      "bbox_pin": null,
      "bbox_name": null
    },
    {
      "pin_number": "26",
      "name": "VCC4_CG2",
      "bbox_pin": null,
      "bbox_name": null
    },
    {
      "pin_number": "27",
      "name": "DCLKOUT6",
      "bbox_pin": null,
      "bbox_name": null
    },
    {
      "pin_number": "28",
      "name": "DCLKOU6",
      "bbox_pin": null,
      "bbox_name": null
    },
    {
      "pin_number": "29",
      "name": "SDCLKPU7",
      "bbox_pin": null,
      "bbox_name": null
    },
    {
      "pin_number": "30",
      "name": "MISS",
      "bbox_pin": null,
      "bbox_name": null
    },
    {
      "pin_number": "31",
      "name": "STATUSS_LD1",
      "bbox_pin": null,
      "bbox_name": null
    },
    {
      "pin_number": "32",
      "name": "CPOU1",
      "bbox_pin": null,
      "bbox_name": null
    },
    {
      "pin_number": "33",
      "name": "VCC5_DIG",
      "bbox_pin": null,
      "bbox_name": null
    },
    {
      "pin_number": "34",
      "name": "CLKIN1/FIN/FBCLKIN",
      "bbox_pin": null,
      "bbox_name": null
    },
    {
      "pin_number": "35",
      "name": "MISS",
      "bbox_pin": null,
      "bbox_name": null
    },
    {
      "pin_number": "36",
      "name": "VCC6_PLL1",
      "bbox_pin": null,
      "bbox_name": null
    },
    {
      "pin_number": "37",
      "name": "CLKIN0",
      "bbox_pin": null,
      "bbox_name": null
    },
    {
      "pin_number": "38",
      "name": "CLKIN*",
      "bbox_pin": null,
      "bbox_name": null
    },
    {
      "pin_number": "39",
      "name": "MISS",
      "bbox_pin": null,
      "bbox_name": null
    },
    {
      "pin_number": "40",
      "name": "MISS",
      "bbox_pin": null,
      "bbox_name": null
    },
    {
      "pin_number": "41",
      "name": "OSCOUT*/CLKIN2*",
      "bbox_pin": null,
      "bbox_name": null
    },
    {
      "pin_number": "42",
      "name": "VCC8_OSCIN",
      "bbox_pin": null,
      "bbox_name": null
    },
    {
      "pin_number": "43",
      "name": "OSCIN",
      "bbox_pin": null,
      "bbox_name": null
    },
    {
      "pin_number": "44",
      "name": "MISS",
      "bbox_pin": null,
      "bbox_name": null
    },
    {
      "pin_number": "45",
      "name": "VCC9_CP2",
      "bbox_pin": null,
      "bbox_name": null
    },
    {
      "pin_number": "46",
      "name": "CPOUT2",
      "bbox_pin": null,
      "bbox_name": null
    },
    {
      "pin_number": "47",
      "name": "VCC10_PLL2",
      "bbox_pin": null,
      "bbox_name": null
    },
    {
      "pin_number": "48",
      "name": "STUS_LD2",
      "bbox_pin": null,
      "bbox_name": null
    },
    {
      "pin_number": "49",
      "name": "MISS",
      "bbox_pin": null,
      "bbox_name": null
    },
    {
      "pin_number": "50",
      "name": "SDCLKOUT9",
      "bbox_pin": null,
      "bbox_name": null
    },
    {
      "pin_number": "51",
      "name": "DCLKOUT8",
      "bbox_pin": null,
      "bbox_name": null
    },
    {
      "pin_number": "52",
      "name": "DCLKOUT",
      "bbox_pin": null,
      "bbox_name": null
    },
    {
      "pin_number": "53",
      "name": "VCC11_CG3",
      "bbox_pin": null,
      "bbox_name": null
    },
    {
      "pin_number": "54",
      "name": "DCLKOUT10",
      "bbox_pin": null,
      "bbox_name": null
    },
    {
      "pin_number": "55",
      "name": "DCLKOUT10",
      "bbox_pin": null,
      "bbox_name": null
    },
    {
      "pin_number": "56",
      "name": "SDCLKOUT1",
      "bbox_pin": null,
      "bbox_name": null
    },
    {
      "pin_number": "57",
      "name": "SDCLKOUT11",
      "bbox_pin": null,
      "bbox_name": null
    },
    {
      "pin_number": "58",
      "name": "CLKIN_SEL0",
      "bbox_pin": null,
      "bbox_name": null
    },
    {
      "pin_number": "59",
      "name": "CLKIN_SEL1",
      "bbox_pin": null,
      "bbox_name": null
    },
    {
      "pin_number": "60",
      "name": "SDCLKOU13",
      "bbox_pin": null,
      "bbox_name": null
    },
    {
      "pin_number": "61",
      "name": "SDCLKOU13",
      "bbox_pin": null,
      "bbox_name": null
    },
    {
      "pin_number": "62",
      "name": "DCLKEU12",
      "bbox_pin": null,
      "bbox_name": null
    },
    {
      "pin_number": "63",
      "name": "DCLKOUT12",
      "bbox_pin": null,
      "bbox_name": null
    },
    {
      "pin_number": "64",
      "name": "VCC12_CG0",
      "bbox_pin": null,
      "bbox_name": null
    }
  ],
  "file_name": "CSCG04828_7_1.jpg"
}