{
  "image_id": "MAX3160-MAX3162_22_1",
  "width": 495,
  "height": 594,
  "total_pins": 24,
  "package_type": "2side",
  "pins": [
    {
      "pin_number": 1,
      "name": "C1+",
      "bbox_pin": null,
      "bbox_name": [
        54,
        39,
        97,
        66
      ]
    },
    {
      "pin_number": 2,
      "name": "VCC",
      "bbox_pin": null,
      "bbox_name": [
        59,
        82,
        96,
        117
      ]
    },
    {
      "pin_number": 3,
      "name": "C1-",
      "bbox_pin": null,
      "bbox_name": [
        62,
        129,
        96,
        153
      ]
    },
    {
      "pin_number": 4,
      "name": "GND",
      "bbox_pin": null,
      "bbox_name": [
        54,
        173,
        98,
        199
      ]
    },
    {
      "pin_number": 5,
      "name": "T1OUT",
      "bbox_pin": null,
      "bbox_name": [
        38,
        216,
        99,
        245
      ]
    },
    {
      "pin_number": 6,
      "name": "Z(B)",
      "bbox_pin": null,
      "bbox_name": [
        51,
        260,
        96,
        287
      ]
    },
    {
      "pin_number": 7,
      "name": "Y(A)",
      "bbox_pin": null,
      "bbox_name": [
        53,
        303,
        96,
        333
      ]
    },
    {
      "pin_number": 8,
      "name": "T2OUT",
      "bbox_pin": null,
      "bbox_name": [
        36,
        345,
        96,
        375
      ]
    },
    {
      "pin_number": 9,
      "name": "R1OUT",
      "bbox_pin": null,
      "bbox_name": [
        38,
        387,
        99,
        420
      ]
    },
    {
      "pin_number": 10,
      "name": "RO/R2OUT",
      "bbox_pin": null,
      "bbox_name": [
        3,
        437,
        99,
        466
      ]
    },
    {
      "pin_number": 11,
      "name": "S\\H\\D\\N\\",
      "bbox_pin": null,
      "bbox_name": [
        42,
        480,
        99,
        505
      ]
    },
    {
      "pin_number": 12,
      "name": "FAST",
      "bbox_pin": null,
      "bbox_name": [
        50,
        520,
        98,
        555
      ]
    },
    {
      "pin_number": 13,
      "name": "RS-485/R\\S\\-\\2\\3\\2\\",
      "bbox_pin": null,
      "bbox_name": [
        359,
        523,
        484,
        555
      ]
    },
    {
      "pin_number": 14,
      "name": "HDPLX",
      "bbox_pin": null,
      "bbox_name": [
        358,
        480,
        420,
        506
      ]
    },
    {
      "pin_number": 15,
      "name": "A",
      "bbox_pin": null,
      "bbox_name": [
        356,
        441,
        381,
        468
      ]
    },
    {
      "pin_number": 16,
      "name": "B",
      "bbox_pin": null,
      "bbox_name": [
        359,
        396,
        380,
        419
      ]
    },
    {
      "pin_number": 17,
      "name": "R2IN",
      "bbox_pin": null,
      "bbox_name": [
        357,
        350,
        405,
        373
      ]
    },
    {
      "pin_number": 18,
      "name": "R1IN",
      "bbox_pin": null,
      "bbox_name": [
        355,
        304,
        403,
        327
      ]
    },
    {
      "pin_number": 19,
      "name": "DE485/T2IN",
      "bbox_pin": null,
      "bbox_name": [
        360,
        262,
        460,
        291
      ]
    },
    {
      "pin_number": 20,
      "name": "DI/T1IN",
      "bbox_pin": null,
      "bbox_name": [
        358,
        219,
        423,
        243
      ]
    },
    {
      "pin_number": 21,
      "name": "V-",
      "bbox_pin": null,
      "bbox_name": [
        360,
        176,
        383,
        196
      ]
    },
    {
      "pin_number": 22,
      "name": "C2-",
      "bbox_pin": null,
      "bbox_name": [
        359,
        134,
        394,
        153
      ]
    },
    {
      "pin_number": 23,
      "name": "C2+",
      "bbox_pin": null,
      "bbox_name": [
        360,
        87,
        402,
        110
      ]
    },
    {
      "pin_number": 24,
      "name": "V+",
      "bbox_pin": null,
      "bbox_name": [
        358,
        40,
        385,
        63
      ]
    }
  ]
}