{
  "image_id": "sn74avc4t245_4_1",
  "width": 561,
  "height": 441,
  "total_pins": 16,
  "package_type": "2side",
  "pins": [
    {
      "pin_number": 1,
      "name": "VCCA",
      "bbox_pin": null,
      "bbox_name": [
        19,
        69,
        70,
        84
      ]
    },
    {
      "pin_number": 2,
      "name": "1DIR",
      "bbox_pin": null,
      "bbox_name": [
        29,
        108,
        67,
        126
      ]
    },
    {
      "pin_number": 3,
      "name": "2DIR",
      "bbox_pin": null,
      "bbox_name": [
        27,
        148,
        68,
        166
      ]
    },
    {
      "pin_number": 4,
      "name": "1A1",
      "bbox_pin": null,
      "bbox_name": [
        36,
        191,
        66,
        206
      ]
    },
    {
      "pin_number": 5,
      "name": "1A2",
      "bbox_pin": null,
      "bbox_name": [
        38,
        230,
        68,
        249
      ]
    },
    {
      "pin_number": 6,
      "name": "2A1",
      "bbox_pin": null,
      "bbox_name": [
        32,
        270,
        66,
        290
      ]
    },
    {
      "pin_number": 7,
      "name": "2A2",
      "bbox_pin": null,
      "bbox_name": [
        36,
        312,
        66,
        329
      ]
    },
    {
      "pin_number": 8,
      "name": "GND",
      "bbox_pin": null,
      "bbox_name": [
        29,
        353,
        66,
        371
      ]
    },
    {
      "pin_number": 9,
      "name": "GND",
      "bbox_pin": null,
      "bbox_name": [
        489,
        352,
        529,
        369
      ]
    },
    {
      "pin_number": 10,
      "name": "2B2",
      "bbox_pin": null,
      "bbox_name": [
        491,
        310,
        521,
        329
      ]
    },
    {
      "pin_number": 11,
      "name": "2B1",
      "bbox_pin": null,
      "bbox_name": [
        489,
        270,
        520,
        287
      ]
    },
    {
      "pin_number": 12,
      "name": "1B2",
      "bbox_pin": null,
      "bbox_name": [
        492,
        230,
        523,
        248
      ]
    },
    {
      "pin_number": 13,
      "name": "1B1",
      "bbox_pin": null,
      "bbox_name": [
        491,
        192,
        523,
        208
      ]
    },
    {
      "pin_number": 14,
      "name": "2 O\\E\\",
      "bbox_pin": null,
      "bbox_name": [
        490,
        147,
        532,
        165
      ]
    },
    {
      "pin_number": 15,
      "name": "1 O\\E\\",
      "bbox_pin": null,
      "bbox_name": [
        493,
        106,
        533,
        126
      ]
    },
    {
      "pin_number": 16,
      "name": "VCCB",
      "bbox_pin": null,
      "bbox_name": [
        490,
        65,
        539,
        85
      ]
    }
  ]
}